polymers-0.3.7.dist-info/METADATA
polymers-0.3.7.dist-info/WHEEL
polymers-0.3.7.dist-info/license_files/LICENSE
polymers/__init__.py
polymers/polymers.cpython-39-darwin.so
polymers-0.3.7.dist-info/RECORD
