Metadata-Version: 2.1
Name: polymers
Version: 0.3.7
Classifier: License :: OSI Approved :: BSD License
Classifier: Development Status :: 5 - Production/Stable
Classifier: Intended Audience :: Science/Research
Classifier: Topic :: Scientific/Engineering
Classifier: Programming Language :: Python
Classifier: Programming Language :: Rust
Requires-Dist: cffi
Requires-Dist: maturin
Requires-Dist: numpy
License-File: LICENSE
Summary: Polymers Modeling Library
Keywords: julia,polymers,python,rust
Author: Michael R. Buche
Author-email: mrbuche@sandia.gov
License: BSD-3-Clause
Requires-Python: >=3.7, <3.12
Project-URL: Documentation, https://polymers.readthedocs.io
Project-URL: Homepage, https://sandialabs.github.io/Polymers
Project-URL: Repository, https://github.com/sandialabs/polymers
